README.txt
setup.cfg
setup.py
collective/__init__.py
collective.pivottable.egg-info/PKG-INFO
collective.pivottable.egg-info/SOURCES.txt
collective.pivottable.egg-info/dependency_links.txt
collective.pivottable.egg-info/entry_points.txt
collective.pivottable.egg-info/namespace_packages.txt
collective.pivottable.egg-info/not-zip-safe
collective.pivottable.egg-info/requires.txt
collective.pivottable.egg-info/top_level.txt
collective/pivottable/__init__.py
collective/pivottable/aggregate_functions.py
collective/pivottable/pivot_table.py
collective/pivottable/testing.txt
docs/HISTORY.txt