Metadata-Version: 1.0
Name: collective.pivottable
Version: 1.1.1dev-r97462
Summary: A class to generate Pivot Tables based on Objects, using your attributes and/or methods, that can use Zope Acquisition to get those.
Home-page: http://dev.plone.org/collective/browser/collective.pivottable
Author: Simples Consultoria - Luciano Pacheco
Author-email: products@simplesconsultoria.com.br
License: GPL
Keywords: plone zope python pivot table pivottable
Platform: UNKNOWN
Classifier: Programming Language :: Python
Classifier: Topic :: Software Development :: Libraries :: Python Modules
